[
    {
        "url": "Thermometor.html",
        "src": "pictures/Thermometor.png",
        "artist_id": 1,
        "page": "clip_art",
        "created_at": ""
    },
    {
        "url": "convertable7.html",
        "src": "pictures/convertable7.jpg",
        "artist_id": 1,
        "page": "clip_art",
        "created_at": ""

    },
    {
        "url": "Thinkonthesethingsnew.html",
        "src": "pictures/Thinkonthesethingsnew.png",
        "artist_id": 1,
        "page": "clip_art",
        "created_at": ""

    },
    {
        "url": "fighters.html",
        "src": "pictures/fighters.PNG",
        "artist_id": 3,
        "page": "sketches",
        "created_at": ""

    }
]